Verilog/flipflop.v
module flip_flop (
    input wire in,
    input wire clk,
    output reg out
);

always @(posedge clk) begin
    out <= in;
end

endmodule

Verilog/flipflop_tb.v
`include "flipflop.v"
module tb_flip_flop;

reg in;
reg clk;
wire out;

flip_flop uut (
    .in(in),
    .clk(clk),
    .out(out)
);

initial begin
    clk = 0;
    forever #5 clk = ~clk;
end

initial begin
    $dumpfile("flipflop.vcd");
    $dumpvars(0, tb_flip_flop);
    in = 0;
    #10;
    
    in = 1;
    #10;
    
    in = 0;
    #10;
    
    in = 1;
    #10;
    
    in = 0;
    #10;
    
    $finish;
end
endmodule

Verilog/flipflop.vcd
$date
	Wed Nov 20 14:35:37 2024
$end
$version
	Icarus Verilog
$end
$timescale
	1s
$end
$scope module tb_flip_flop $end
$var wire 1 ! out $end
$var reg 1 " clk $end
$var reg 1 # in $end
$scope module uut $end
$var wire 1 " clk $end
$var wire 1 # in $end
$var reg 1 ! out $end
$upscope $end
$upscope $end
$enddefinitions $end
$comment Show the parameter values. $end
$dumpall
$end
#0
$dumpvars
0#
0"
x!
$end
#5
0!
1"
#10
0"
1#
#15
1!
1"
#20
0"
0#
#25
0!
1"
#30
0"
1#
#35
1!
1"
#40
0"
0#
#45
0!
1"
